{
    "generated_at_utc":  "2026-04-08T21:29:48Z",
    "total_events":  1283,
    "source_map_url":  "https://earthquake.usgs.gov/earthquakes/map/?extent=14.64737,-144.22852\u0026extent=56.31654,-45.79102\u0026range=week\u0026magnitude=all",
    "coverage":  {
                     "earliest_event_time_utc":  "2026-04-01T21:30:15Z",
                     "latest_event_time_utc":  "2026-04-08T21:20:43Z",
                     "earliest_event_time_et":  "2026-04-01T17:30:15-04:00",
                     "latest_event_time_et":  "2026-04-08T17:20:43-04:00"
                 },
    "summary":  {
                    "countries_count":  9,
                    "max_magnitude":  4.8,
                    "avg_magnitude":  1.47,
                    "avg_depth_km":  8,
                    "reviewed_events":  842,
                    "automatic_events":  441,
                    "felt_events":  50,
                    "significant_events":  7
                },
    "scope":  {
                  "has_extent_filter":  true
              }
}
