{
    "generated_at_utc":  "2026-04-08T10:43:21Z",
    "total_events":  1291,
    "source_map_url":  "https://earthquake.usgs.gov/earthquakes/map/?extent=14.64737,-144.22852\u0026extent=56.31654,-45.79102\u0026range=week\u0026magnitude=all",
    "coverage":  {
                     "earliest_event_time_utc":  "2026-04-01T11:16:49Z",
                     "latest_event_time_utc":  "2026-04-08T09:44:00Z",
                     "earliest_event_time_et":  "2026-04-01T07:16:49-04:00",
                     "latest_event_time_et":  "2026-04-08T05:44:00-04:00"
                 },
    "summary":  {
                    "countries_count":  8,
                    "max_magnitude":  4.6,
                    "avg_magnitude":  1.48,
                    "avg_depth_km":  8,
                    "reviewed_events":  827,
                    "automatic_events":  464,
                    "felt_events":  51,
                    "significant_events":  7
                },
    "scope":  {
                  "has_extent_filter":  true
              }
}
