{
    "generated_at_utc":  "2026-03-16T05:58:43Z",
    "total_events":  1193,
    "source_map_url":  "https://earthquake.usgs.gov/earthquakes/map/?extent=14.64737,-144.22852\u0026extent=56.31654,-45.79102\u0026range=week\u0026magnitude=all",
    "coverage":  {
                     "earliest_event_time_utc":  "2026-03-09T06:03:08Z",
                     "latest_event_time_utc":  "2026-03-16T05:48:21Z",
                     "earliest_event_time_et":  "2026-03-09T02:03:08-04:00",
                     "latest_event_time_et":  "2026-03-16T01:48:21-04:00"
                 },
    "summary":  {
                    "countries_count":  9,
                    "max_magnitude":  5.1,
                    "avg_magnitude":  1.44,
                    "avg_depth_km":  6.8,
                    "reviewed_events":  624,
                    "automatic_events":  569,
                    "felt_events":  49,
                    "significant_events":  8
                },
    "scope":  {
                  "has_extent_filter":  true
              }
}
