{
    "generated_at_utc":  "2026-03-22T18:46:06Z",
    "total_events":  1231,
    "source_map_url":  "https://earthquake.usgs.gov/earthquakes/map/?extent=14.64737,-144.22852\u0026extent=56.31654,-45.79102\u0026range=week\u0026magnitude=all",
    "coverage":  {
                     "earliest_event_time_utc":  "2026-03-15T18:45:51Z",
                     "latest_event_time_utc":  "2026-03-22T18:02:45Z",
                     "earliest_event_time_et":  "2026-03-15T14:45:51-04:00",
                     "latest_event_time_et":  "2026-03-22T14:02:45-04:00"
                 },
    "summary":  {
                    "countries_count":  11,
                    "max_magnitude":  6.6,
                    "avg_magnitude":  1.44,
                    "avg_depth_km":  7.8,
                    "reviewed_events":  733,
                    "automatic_events":  498,
                    "felt_events":  45,
                    "significant_events":  13
                },
    "scope":  {
                  "has_extent_filter":  true
              }
}
