{
    "generated_at_utc":  "2026-04-06T19:06:11Z",
    "total_events":  1342,
    "source_map_url":  "https://earthquake.usgs.gov/earthquakes/map/?extent=14.64737,-144.22852\u0026extent=56.31654,-45.79102\u0026range=week\u0026magnitude=all",
    "coverage":  {
                     "earliest_event_time_utc":  "2026-03-30T19:10:03Z",
                     "latest_event_time_utc":  "2026-04-06T18:58:25Z",
                     "earliest_event_time_et":  "2026-03-30T15:10:03-04:00",
                     "latest_event_time_et":  "2026-04-06T14:58:25-04:00"
                 },
    "summary":  {
                    "countries_count":  7,
                    "max_magnitude":  5,
                    "avg_magnitude":  1.57,
                    "avg_depth_km":  8.9,
                    "reviewed_events":  875,
                    "automatic_events":  467,
                    "felt_events":  45,
                    "significant_events":  11
                },
    "scope":  {
                  "has_extent_filter":  true
              }
}
