{
    "generated_at_utc":  "2026-03-28T21:42:37Z",
    "total_events":  1217,
    "source_map_url":  "https://earthquake.usgs.gov/earthquakes/map/?extent=14.64737,-144.22852\u0026extent=56.31654,-45.79102\u0026range=week\u0026magnitude=all",
    "coverage":  {
                     "earliest_event_time_utc":  "2026-03-21T22:01:13Z",
                     "latest_event_time_utc":  "2026-03-28T21:32:46Z",
                     "earliest_event_time_et":  "2026-03-21T18:01:13-04:00",
                     "latest_event_time_et":  "2026-03-28T17:32:46-04:00"
                 },
    "summary":  {
                    "countries_count":  9,
                    "max_magnitude":  5.1,
                    "avg_magnitude":  1.43,
                    "avg_depth_km":  7.6,
                    "reviewed_events":  797,
                    "automatic_events":  420,
                    "felt_events":  48,
                    "significant_events":  14
                },
    "scope":  {
                  "has_extent_filter":  true
              }
}
